[
  {
    "id": "wikipedia:1289332429",
    "type": "wikipedia",
    "timestamp": "2025-05-07T23:18:08Z",
    "title": "edited \"Dropout (streaming service)\"",
    "summary": "Note pay share in 2024 as well (+51 bytes)",
    "url": "https://en.wikipedia.org/w/index.php?title=Dropout%20(streaming%20service)&diff=1289332429&oldid=1289331645",
    "content_html": "\n    <p><strong>Edit to:</strong> <a href=\"https://en.wikipedia.org/wiki/Dropout%20(streaming%20service)\" target=\"_blank\" rel=\"noopener\">Dropout (streaming service)</a></p>\n    <p><strong>Summary:</strong> Note pay share in 2024 as well</p>\n    <p><strong>Size change:</strong> <span style=\"color: #7cb342;\">+51 bytes</span></p>\n    <p><a href=\"https://en.wikipedia.org/w/index.php?title=Dropout%20(streaming%20service)&diff=1289332429&oldid=1289331645\" target=\"_blank\" rel=\"noopener\" style=\"color: var(--accent);\">View diff →</a></p>\n  ",
    "metadata": {
      "page": "Dropout (streaming service)",
      "diff": 1289332429,
      "oldid": 1289331645,
      "size_delta": 51,
      "comment": "Note pay share in 2024 as well"
    }
  },
  {
    "id": "wikipedia:1289331645",
    "type": "wikipedia",
    "timestamp": "2025-05-07T23:10:20Z",
    "title": "edited \"Dropout (streaming service)\"",
    "summary": "Past tense for Vimeo use",
    "url": "https://en.wikipedia.org/w/index.php?title=Dropout%20(streaming%20service)&diff=1289331645&oldid=1289021402",
    "content_html": "\n    <p><strong>Edit to:</strong> <a href=\"https://en.wikipedia.org/wiki/Dropout%20(streaming%20service)\" target=\"_blank\" rel=\"noopener\">Dropout (streaming service)</a></p>\n    <p><strong>Summary:</strong> Past tense for Vimeo use</p>\n    \n    <p><a href=\"https://en.wikipedia.org/w/index.php?title=Dropout%20(streaming%20service)&diff=1289331645&oldid=1289021402\" target=\"_blank\" rel=\"noopener\" style=\"color: var(--accent);\">View diff →</a></p>\n  ",
    "metadata": {
      "page": "Dropout (streaming service)",
      "diff": 1289331645,
      "oldid": 1289021402,
      "size_delta": 0,
      "comment": "Past tense for Vimeo use"
    }
  },
  {
    "id": "wikipedia:1230993824",
    "type": "wikipedia",
    "timestamp": "2024-06-25T21:14:32Z",
    "title": "edited \"Transformer (deep learning architecture)\"",
    "summary": "move citation required reference to match assertion in comma separated list (-1 bytes)",
    "url": "https://en.wikipedia.org/w/index.php?title=Transformer%20(deep%20learning%20architecture)&diff=1230993824&oldid=1230692458",
    "content_html": "\n    <p><strong>Edit to:</strong> <a href=\"https://en.wikipedia.org/wiki/Transformer%20(deep%20learning%20architecture)\" target=\"_blank\" rel=\"noopener\">Transformer (deep learning architecture)</a></p>\n    <p><strong>Summary:</strong> move citation required reference to match assertion in comma separated list</p>\n    <p><strong>Size change:</strong> <span style=\"color: #e53935;\">-1 bytes</span></p>\n    <p><a href=\"https://en.wikipedia.org/w/index.php?title=Transformer%20(deep%20learning%20architecture)&diff=1230993824&oldid=1230692458\" target=\"_blank\" rel=\"noopener\" style=\"color: var(--accent);\">View diff →</a></p>\n  ",
    "metadata": {
      "page": "Transformer (deep learning architecture)",
      "diff": 1230993824,
      "oldid": 1230692458,
      "size_delta": -1,
      "comment": "move citation required reference to match assertion in comma separated list"
    }
  },
  {
    "id": "wikipedia:1230990283",
    "type": "wikipedia",
    "timestamp": "2024-06-25T20:50:31Z",
    "title": "trimmed \"User talk:Chasemp\"",
    "summary": "[[WP:AES|←]]Replaced content with ' == A kitten for you! ==  [[File:Kitten (06) by Ron.jpg|left|150px]] Thank you for your edits to [[Armpit fart]]  [[User:Hashar|Hashar]] ([[User talk:Hashar|talk]]) ",
    "url": "https://en.wikipedia.org/w/index.php?title=User%20talk%3AChasemp&diff=1230990283&oldid=1061831731",
    "content_html": "\n    <p><strong>Edit to:</strong> <a href=\"https://en.wikipedia.org/wiki/User%20talk%3AChasemp\" target=\"_blank\" rel=\"noopener\">User talk:Chasemp</a></p>\n    <p><strong>Summary:</strong> [[WP:AES|←]]Replaced content with ' == A kitten for you! ==  [[File:Kitten (06) by Ron.jpg|left|150px]] Thank you for your edits to [[Armpit fart]]  [[User:Hashar|Hashar]] ([[User talk:Hashar|talk]]) 20:26, 22 February 2019 (UTC) <br style=\"clear: both;\"/>'</p>\n    <p><strong>Size change:</strong> <span style=\"color: #e53935;\">-47246 bytes</span></p>\n    <p><a href=\"https://en.wikipedia.org/w/index.php?title=User%20talk%3AChasemp&diff=1230990283&oldid=1061831731\" target=\"_blank\" rel=\"noopener\" style=\"color: var(--accent);\">View diff →</a></p>\n  ",
    "metadata": {
      "page": "User talk:Chasemp",
      "diff": 1230990283,
      "oldid": 1061831731,
      "size_delta": -47246,
      "comment": "[[WP:AES|←]]Replaced content with ' == A kitten for you! ==  [[File:Kitten (06) by Ron.jpg|left|150px]] Thank you for your edits to [[Armpit fart]]  [[User:Hashar|Hashar]] ([[User talk:Hashar|talk]]) 20:26, 22 February 2019 (UTC) <br style=\"clear: both;\"/>'"
    }
  },
  {
    "id": "wikipedia:1230990037",
    "type": "wikipedia",
    "timestamp": "2024-06-25T20:49:09Z",
    "title": "edited \"Artificial intelligence\"",
    "summary": "It is unclear what \"After the U.S. election in 2016, major technology companies took steps to mitigate the problem\" is referring too.  Marked for needed citation. (+118 bytes)",
    "url": "https://en.wikipedia.org/w/index.php?title=Artificial%20intelligence&diff=1230990037&oldid=1230878798",
    "content_html": "\n    <p><strong>Edit to:</strong> <a href=\"https://en.wikipedia.org/wiki/Artificial%20intelligence\" target=\"_blank\" rel=\"noopener\">Artificial intelligence</a></p>\n    <p><strong>Summary:</strong> It is unclear what \"After the U.S. election in 2016, major technology companies took steps to mitigate the problem\" is referring too.  Marked for needed citation.</p>\n    <p><strong>Size change:</strong> <span style=\"color: #7cb342;\">+118 bytes</span></p>\n    <p><a href=\"https://en.wikipedia.org/w/index.php?title=Artificial%20intelligence&diff=1230990037&oldid=1230878798\" target=\"_blank\" rel=\"noopener\" style=\"color: var(--accent);\">View diff →</a></p>\n  ",
    "metadata": {
      "page": "Artificial intelligence",
      "diff": 1230990037,
      "oldid": 1230878798,
      "size_delta": 118,
      "comment": "It is unclear what \"After the U.S. election in 2016, major technology companies took steps to mitigate the problem\" is referring too.  Marked for needed citation."
    }
  },
  {
    "id": "wikipedia:1116735851",
    "type": "wikipedia",
    "timestamp": "2022-10-18T02:13:08Z",
    "title": "edited \"Wikipedia:Scripts++/Subscribe\"",
    "summary": "No edit summary (-62 bytes)",
    "url": "https://en.wikipedia.org/w/index.php?title=Wikipedia%3AScripts%2B%2B%2FSubscribe&diff=1116735851&oldid=1114937705",
    "content_html": "\n    <p><strong>Edit to:</strong> <a href=\"https://en.wikipedia.org/wiki/Wikipedia%3AScripts%2B%2B%2FSubscribe\" target=\"_blank\" rel=\"noopener\">Wikipedia:Scripts++/Subscribe</a></p>\n    <p><strong>Summary:</strong> No edit summary</p>\n    <p><strong>Size change:</strong> <span style=\"color: #e53935;\">-62 bytes</span></p>\n    <p><a href=\"https://en.wikipedia.org/w/index.php?title=Wikipedia%3AScripts%2B%2B%2FSubscribe&diff=1116735851&oldid=1114937705\" target=\"_blank\" rel=\"noopener\" style=\"color: var(--accent);\">View diff →</a></p>\n  ",
    "metadata": {
      "page": "Wikipedia:Scripts++/Subscribe",
      "diff": 1116735851,
      "oldid": 1114937705,
      "size_delta": -62,
      "comment": "No edit summary"
    }
  },
  {
    "id": "wikipedia:1116110289",
    "type": "wikipedia",
    "timestamp": "2022-10-14T21:26:53Z",
    "title": "edited \"X.509\"",
    "summary": "/* Problems with certification authorities */ update future statement from 2018 with present (-30 bytes)",
    "url": "https://en.wikipedia.org/w/index.php?title=X.509&diff=1116110289&oldid=1115035574",
    "content_html": "\n    <p><strong>Edit to:</strong> <a href=\"https://en.wikipedia.org/wiki/X.509\" target=\"_blank\" rel=\"noopener\">X.509</a></p>\n    <p><strong>Summary:</strong> /* Problems with certification authorities */ update future statement from 2018 with present</p>\n    <p><strong>Size change:</strong> <span style=\"color: #e53935;\">-30 bytes</span></p>\n    <p><a href=\"https://en.wikipedia.org/w/index.php?title=X.509&diff=1116110289&oldid=1115035574\" target=\"_blank\" rel=\"noopener\" style=\"color: var(--accent);\">View diff →</a></p>\n  ",
    "metadata": {
      "page": "X.509",
      "diff": 1116110289,
      "oldid": 1115035574,
      "size_delta": -30,
      "comment": "/* Problems with certification authorities */ update future statement from 2018 with present"
    }
  },
  {
    "id": "wikipedia:1030445861",
    "type": "wikipedia",
    "timestamp": "2021-06-25T23:43:50Z",
    "title": "edited \"List of Scientologists\"",
    "summary": "/* Current Scientologists */ Fixed typo (-1 bytes)",
    "url": "https://en.wikipedia.org/w/index.php?title=List%20of%20Scientologists&diff=1030445861&oldid=1030096929",
    "content_html": "\n    <p><strong>Edit to:</strong> <a href=\"https://en.wikipedia.org/wiki/List%20of%20Scientologists\" target=\"_blank\" rel=\"noopener\">List of Scientologists</a></p>\n    <p><strong>Summary:</strong> /* Current Scientologists */ Fixed typo</p>\n    <p><strong>Size change:</strong> <span style=\"color: #e53935;\">-1 bytes</span></p>\n    <p><a href=\"https://en.wikipedia.org/w/index.php?title=List%20of%20Scientologists&diff=1030445861&oldid=1030096929\" target=\"_blank\" rel=\"noopener\" style=\"color: var(--accent);\">View diff →</a></p>\n  ",
    "metadata": {
      "page": "List of Scientologists",
      "diff": 1030445861,
      "oldid": 1030096929,
      "size_delta": -1,
      "comment": "/* Current Scientologists */ Fixed typo"
    }
  },
  {
    "id": "wikipedia:1016683443",
    "type": "wikipedia",
    "timestamp": "2021-04-08T14:48:21Z",
    "title": "edited \"Tom Everett Scott\"",
    "summary": "/* Tom Everett Scott */ it is cancelled (+2 bytes)",
    "url": "https://en.wikipedia.org/w/index.php?title=Tom%20Everett%20Scott&diff=1016683443&oldid=1016679916",
    "content_html": "\n    <p><strong>Edit to:</strong> <a href=\"https://en.wikipedia.org/wiki/Tom%20Everett%20Scott\" target=\"_blank\" rel=\"noopener\">Tom Everett Scott</a></p>\n    <p><strong>Summary:</strong> /* Tom Everett Scott */ it is cancelled</p>\n    <p><strong>Size change:</strong> <span style=\"color: #7cb342;\">+2 bytes</span></p>\n    <p><a href=\"https://en.wikipedia.org/w/index.php?title=Tom%20Everett%20Scott&diff=1016683443&oldid=1016679916\" target=\"_blank\" rel=\"noopener\" style=\"color: var(--accent);\">View diff →</a></p>\n  ",
    "metadata": {
      "page": "Tom Everett Scott",
      "diff": 1016683443,
      "oldid": 1016679916,
      "size_delta": 2,
      "comment": "/* Tom Everett Scott */ it is cancelled"
    }
  },
  {
    "id": "wikipedia:1016679916",
    "type": "wikipedia",
    "timestamp": "2021-04-08T14:26:19Z",
    "title": "edited \"Tom Everett Scott\"",
    "summary": "/* Tom Everett Scott */ (+21 bytes)",
    "url": "https://en.wikipedia.org/w/index.php?title=Tom%20Everett%20Scott&diff=1016679916&oldid=1016118030",
    "content_html": "\n    <p><strong>Edit to:</strong> <a href=\"https://en.wikipedia.org/wiki/Tom%20Everett%20Scott\" target=\"_blank\" rel=\"noopener\">Tom Everett Scott</a></p>\n    <p><strong>Summary:</strong> /* Tom Everett Scott */</p>\n    <p><strong>Size change:</strong> <span style=\"color: #7cb342;\">+21 bytes</span></p>\n    <p><a href=\"https://en.wikipedia.org/w/index.php?title=Tom%20Everett%20Scott&diff=1016679916&oldid=1016118030\" target=\"_blank\" rel=\"noopener\" style=\"color: var(--accent);\">View diff →</a></p>\n  ",
    "metadata": {
      "page": "Tom Everett Scott",
      "diff": 1016679916,
      "oldid": 1016118030,
      "size_delta": 21,
      "comment": "/* Tom Everett Scott */"
    }
  },
  {
    "id": "wikipedia:973843581",
    "type": "wikipedia",
    "timestamp": "2020-08-19T15:05:22Z",
    "title": "edited \"Theodore Roosevelt\"",
    "summary": "Introduce civic offices together and chronologically for lead in paragraph for clarity on arc of service (-16 bytes)",
    "url": "https://en.wikipedia.org/w/index.php?title=Theodore%20Roosevelt&diff=973843581&oldid=973769753",
    "content_html": "\n    <p><strong>Edit to:</strong> <a href=\"https://en.wikipedia.org/wiki/Theodore%20Roosevelt\" target=\"_blank\" rel=\"noopener\">Theodore Roosevelt</a></p>\n    <p><strong>Summary:</strong> Introduce civic offices together and chronologically for lead in paragraph for clarity on arc of service</p>\n    <p><strong>Size change:</strong> <span style=\"color: #e53935;\">-16 bytes</span></p>\n    <p><a href=\"https://en.wikipedia.org/w/index.php?title=Theodore%20Roosevelt&diff=973843581&oldid=973769753\" target=\"_blank\" rel=\"noopener\" style=\"color: var(--accent);\">View diff →</a></p>\n  ",
    "metadata": {
      "page": "Theodore Roosevelt",
      "diff": 973843581,
      "oldid": 973769753,
      "size_delta": -16,
      "comment": "Introduce civic offices together and chronologically for lead in paragraph for clarity on arc of service"
    }
  },
  {
    "id": "wikipedia:972629843",
    "type": "wikipedia",
    "timestamp": "2020-08-13T03:08:17Z",
    "title": "edited \"Jack Kornfield\"",
    "summary": "/* Jack Kornfield */ Fixed grammar (+1 bytes)",
    "url": "https://en.wikipedia.org/w/index.php?title=Jack%20Kornfield&diff=972629843&oldid=969295883",
    "content_html": "\n    <p><strong>Edit to:</strong> <a href=\"https://en.wikipedia.org/wiki/Jack%20Kornfield\" target=\"_blank\" rel=\"noopener\">Jack Kornfield</a></p>\n    <p><strong>Summary:</strong> /* Jack Kornfield */ Fixed grammar</p>\n    <p><strong>Size change:</strong> <span style=\"color: #7cb342;\">+1 bytes</span></p>\n    <p><a href=\"https://en.wikipedia.org/w/index.php?title=Jack%20Kornfield&diff=972629843&oldid=969295883\" target=\"_blank\" rel=\"noopener\" style=\"color: var(--accent);\">View diff →</a></p>\n  ",
    "metadata": {
      "page": "Jack Kornfield",
      "diff": 972629843,
      "oldid": 969295883,
      "size_delta": 1,
      "comment": "/* Jack Kornfield */ Fixed grammar"
    }
  },
  {
    "id": "wikipedia:972629458",
    "type": "wikipedia",
    "timestamp": "2020-08-13T03:05:58Z",
    "title": "edited \"French cleat\"",
    "summary": "/* French cleat */ later is ill defined, when in use is accurate (+7 bytes)",
    "url": "https://en.wikipedia.org/w/index.php?title=French%20cleat&diff=972629458&oldid=959031110",
    "content_html": "\n    <p><strong>Edit to:</strong> <a href=\"https://en.wikipedia.org/wiki/French%20cleat\" target=\"_blank\" rel=\"noopener\">French cleat</a></p>\n    <p><strong>Summary:</strong> /* French cleat */ later is ill defined, when in use is accurate</p>\n    <p><strong>Size change:</strong> <span style=\"color: #7cb342;\">+7 bytes</span></p>\n    <p><a href=\"https://en.wikipedia.org/w/index.php?title=French%20cleat&diff=972629458&oldid=959031110\" target=\"_blank\" rel=\"noopener\" style=\"color: var(--accent);\">View diff →</a></p>\n  ",
    "metadata": {
      "page": "French cleat",
      "diff": 972629458,
      "oldid": 959031110,
      "size_delta": 7,
      "comment": "/* French cleat */ later is ill defined, when in use is accurate"
    }
  },
  {
    "id": "wikipedia:972629018",
    "type": "wikipedia",
    "timestamp": "2020-08-13T03:02:55Z",
    "title": "edited \"Secular Buddhism\"",
    "summary": "/* Key concepts and practices */ deploy implies active and even hostile action, impart is more precise.",
    "url": "https://en.wikipedia.org/w/index.php?title=Secular%20Buddhism&diff=972629018&oldid=961329214",
    "content_html": "\n    <p><strong>Edit to:</strong> <a href=\"https://en.wikipedia.org/wiki/Secular%20Buddhism\" target=\"_blank\" rel=\"noopener\">Secular Buddhism</a></p>\n    <p><strong>Summary:</strong> /* Key concepts and practices */ deploy implies active and even hostile action, impart is more precise.</p>\n    \n    <p><a href=\"https://en.wikipedia.org/w/index.php?title=Secular%20Buddhism&diff=972629018&oldid=961329214\" target=\"_blank\" rel=\"noopener\" style=\"color: var(--accent);\">View diff →</a></p>\n  ",
    "metadata": {
      "page": "Secular Buddhism",
      "diff": 972629018,
      "oldid": 961329214,
      "size_delta": 0,
      "comment": "/* Key concepts and practices */ deploy implies active and even hostile action, impart is more precise."
    }
  },
  {
    "id": "wikipedia:972627797",
    "type": "wikipedia",
    "timestamp": "2020-08-13T02:53:44Z",
    "title": "edited \"History of Buddhism\"",
    "summary": "/* South and Southeast Asia */ Fixed typo (-1 bytes)",
    "url": "https://en.wikipedia.org/w/index.php?title=History%20of%20Buddhism&diff=972627797&oldid=972627070",
    "content_html": "\n    <p><strong>Edit to:</strong> <a href=\"https://en.wikipedia.org/wiki/History%20of%20Buddhism\" target=\"_blank\" rel=\"noopener\">History of Buddhism</a></p>\n    <p><strong>Summary:</strong> /* South and Southeast Asia */ Fixed typo</p>\n    <p><strong>Size change:</strong> <span style=\"color: #e53935;\">-1 bytes</span></p>\n    <p><a href=\"https://en.wikipedia.org/w/index.php?title=History%20of%20Buddhism&diff=972627797&oldid=972627070\" target=\"_blank\" rel=\"noopener\" style=\"color: var(--accent);\">View diff →</a></p>\n  ",
    "metadata": {
      "page": "History of Buddhism",
      "diff": 972627797,
      "oldid": 972627070,
      "size_delta": -1,
      "comment": "/* South and Southeast Asia */ Fixed typo"
    }
  },
  {
    "id": "wikipedia:972627070",
    "type": "wikipedia",
    "timestamp": "2020-08-13T02:48:22Z",
    "title": "edited \"History of Buddhism\"",
    "summary": "/* Southeast Asian Buddhism */ Fixed grammar",
    "url": "https://en.wikipedia.org/w/index.php?title=History%20of%20Buddhism&diff=972627070&oldid=969921778",
    "content_html": "\n    <p><strong>Edit to:</strong> <a href=\"https://en.wikipedia.org/wiki/History%20of%20Buddhism\" target=\"_blank\" rel=\"noopener\">History of Buddhism</a></p>\n    <p><strong>Summary:</strong> /* Southeast Asian Buddhism */ Fixed grammar</p>\n    \n    <p><a href=\"https://en.wikipedia.org/w/index.php?title=History%20of%20Buddhism&diff=972627070&oldid=969921778\" target=\"_blank\" rel=\"noopener\" style=\"color: var(--accent);\">View diff →</a></p>\n  ",
    "metadata": {
      "page": "History of Buddhism",
      "diff": 972627070,
      "oldid": 969921778,
      "size_delta": 0,
      "comment": "/* Southeast Asian Buddhism */ Fixed grammar"
    }
  },
  {
    "id": "wikipedia:971339160",
    "type": "wikipedia",
    "timestamp": "2020-08-05T14:17:30Z",
    "title": "edited \"Nicole Galloway\"",
    "summary": "Galloway is the official democratic nominee as of yesterday (+340 bytes)",
    "url": "https://en.wikipedia.org/w/index.php?title=Nicole%20Galloway&diff=971339160&oldid=971328343",
    "content_html": "\n    <p><strong>Edit to:</strong> <a href=\"https://en.wikipedia.org/wiki/Nicole%20Galloway\" target=\"_blank\" rel=\"noopener\">Nicole Galloway</a></p>\n    <p><strong>Summary:</strong> Galloway is the official democratic nominee as of yesterday</p>\n    <p><strong>Size change:</strong> <span style=\"color: #7cb342;\">+340 bytes</span></p>\n    <p><a href=\"https://en.wikipedia.org/w/index.php?title=Nicole%20Galloway&diff=971339160&oldid=971328343\" target=\"_blank\" rel=\"noopener\" style=\"color: var(--accent);\">View diff →</a></p>\n  ",
    "metadata": {
      "page": "Nicole Galloway",
      "diff": 971339160,
      "oldid": 971328343,
      "size_delta": 340,
      "comment": "Galloway is the official democratic nominee as of yesterday"
    }
  },
  {
    "id": "wikipedia:957626625",
    "type": "wikipedia",
    "timestamp": "2020-05-19T19:20:22Z",
    "title": "trimmed \"User talk:Chasemp\"",
    "summary": "[[WP:AES|←]]Replaced content with '== Welcome! ==  Hello, Chasemp, and welcome to Wikipedia! Thank you for [[Special:Contributions/Chasemp|your contributions]]. I hope you like the place and d...' (-4",
    "url": "https://en.wikipedia.org/w/index.php?title=User%20talk%3AChasemp&diff=957626625&oldid=954321079",
    "content_html": "\n    <p><strong>Edit to:</strong> <a href=\"https://en.wikipedia.org/wiki/User%20talk%3AChasemp\" target=\"_blank\" rel=\"noopener\">User talk:Chasemp</a></p>\n    <p><strong>Summary:</strong> [[WP:AES|←]]Replaced content with '== Welcome! ==  Hello, Chasemp, and welcome to Wikipedia! Thank you for [[Special:Contributions/Chasemp|your contributions]]. I hope you like the place and d...'</p>\n    <p><strong>Size change:</strong> <span style=\"color: #e53935;\">-43364 bytes</span></p>\n    <p><a href=\"https://en.wikipedia.org/w/index.php?title=User%20talk%3AChasemp&diff=957626625&oldid=954321079\" target=\"_blank\" rel=\"noopener\" style=\"color: var(--accent);\">View diff →</a></p>\n  ",
    "metadata": {
      "page": "User talk:Chasemp",
      "diff": 957626625,
      "oldid": 954321079,
      "size_delta": -43364,
      "comment": "[[WP:AES|←]]Replaced content with '== Welcome! ==  Hello, Chasemp, and welcome to Wikipedia! Thank you for [[Special:Contributions/Chasemp|your contributions]]. I hope you like the place and d...'"
    }
  },
  {
    "id": "wikipedia:937604950",
    "type": "wikipedia",
    "timestamp": "2020-01-26T02:21:48Z",
    "title": "edited \"Backward running\"",
    "summary": "change wording for speeding up (+16 bytes)",
    "url": "https://en.wikipedia.org/w/index.php?title=Backward%20running&diff=937604950&oldid=936468533",
    "content_html": "\n    <p><strong>Edit to:</strong> <a href=\"https://en.wikipedia.org/wiki/Backward%20running\" target=\"_blank\" rel=\"noopener\">Backward running</a></p>\n    <p><strong>Summary:</strong> change wording for speeding up</p>\n    <p><strong>Size change:</strong> <span style=\"color: #7cb342;\">+16 bytes</span></p>\n    <p><a href=\"https://en.wikipedia.org/w/index.php?title=Backward%20running&diff=937604950&oldid=936468533\" target=\"_blank\" rel=\"noopener\" style=\"color: var(--accent);\">View diff →</a></p>\n  ",
    "metadata": {
      "page": "Backward running",
      "diff": 937604950,
      "oldid": 936468533,
      "size_delta": 16,
      "comment": "change wording for speeding up"
    }
  },
  {
    "id": "wikipedia:937603780",
    "type": "wikipedia",
    "timestamp": "2020-01-26T02:09:56Z",
    "title": "edited \"Waupaca (town), Wisconsin\"",
    "summary": "Typo",
    "url": "https://en.wikipedia.org/w/index.php?title=Waupaca%20(town)%2C%20Wisconsin&diff=937603780&oldid=898232511",
    "content_html": "\n    <p><strong>Edit to:</strong> <a href=\"https://en.wikipedia.org/wiki/Waupaca%20(town)%2C%20Wisconsin\" target=\"_blank\" rel=\"noopener\">Waupaca (town), Wisconsin</a></p>\n    <p><strong>Summary:</strong> Typo</p>\n    \n    <p><a href=\"https://en.wikipedia.org/w/index.php?title=Waupaca%20(town)%2C%20Wisconsin&diff=937603780&oldid=898232511\" target=\"_blank\" rel=\"noopener\" style=\"color: var(--accent);\">View diff →</a></p>\n  ",
    "metadata": {
      "page": "Waupaca (town), Wisconsin",
      "diff": 937603780,
      "oldid": 898232511,
      "size_delta": 0,
      "comment": "Typo"
    }
  },
  {
    "id": "wikipedia:929853585",
    "type": "wikipedia",
    "timestamp": "2019-12-08T17:45:41Z",
    "title": "edited \"Armpit fart\"",
    "summary": "Undid revision 921324748 by [[Special:Contributions/174.89.174.63|174.89.174.63]] ([[User talk:174.89.174.63|talk]]) (+2 bytes)",
    "url": "https://en.wikipedia.org/w/index.php?title=Armpit%20fart&diff=929853585&oldid=921324748",
    "content_html": "\n    <p><strong>Edit to:</strong> <a href=\"https://en.wikipedia.org/wiki/Armpit%20fart\" target=\"_blank\" rel=\"noopener\">Armpit fart</a></p>\n    <p><strong>Summary:</strong> Undid revision 921324748 by [[Special:Contributions/174.89.174.63|174.89.174.63]] ([[User talk:174.89.174.63|talk]])</p>\n    <p><strong>Size change:</strong> <span style=\"color: #7cb342;\">+2 bytes</span></p>\n    <p><a href=\"https://en.wikipedia.org/w/index.php?title=Armpit%20fart&diff=929853585&oldid=921324748\" target=\"_blank\" rel=\"noopener\" style=\"color: var(--accent);\">View diff →</a></p>\n  ",
    "metadata": {
      "page": "Armpit fart",
      "diff": 929853585,
      "oldid": 921324748,
      "size_delta": 2,
      "comment": "Undid revision 921324748 by [[Special:Contributions/174.89.174.63|174.89.174.63]] ([[User talk:174.89.174.63|talk]])"
    }
  },
  {
    "id": "wikipedia:887962170",
    "type": "wikipedia",
    "timestamp": "2019-03-16T00:04:56Z",
    "title": "edited \"User:Chasemp\"",
    "summary": "No edit summary (+58 bytes)",
    "url": "https://en.wikipedia.org/w/index.php?title=User%3AChasemp&diff=887962170&oldid=887476434",
    "content_html": "\n    <p><strong>Edit to:</strong> <a href=\"https://en.wikipedia.org/wiki/User%3AChasemp\" target=\"_blank\" rel=\"noopener\">User:Chasemp</a></p>\n    <p><strong>Summary:</strong> No edit summary</p>\n    <p><strong>Size change:</strong> <span style=\"color: #7cb342;\">+58 bytes</span></p>\n    <p><a href=\"https://en.wikipedia.org/w/index.php?title=User%3AChasemp&diff=887962170&oldid=887476434\" target=\"_blank\" rel=\"noopener\" style=\"color: var(--accent);\">View diff →</a></p>\n  ",
    "metadata": {
      "page": "User:Chasemp",
      "diff": 887962170,
      "oldid": 887476434,
      "size_delta": 58,
      "comment": "No edit summary"
    }
  },
  {
    "id": "wikipedia:887476434",
    "type": "wikipedia",
    "timestamp": "2019-03-12T22:28:21Z",
    "title": "edited \"User:Chasemp\"",
    "summary": "No edit summary (+12 bytes)",
    "url": "https://en.wikipedia.org/w/index.php?title=User%3AChasemp&diff=887476434&oldid=672942728",
    "content_html": "\n    <p><strong>Edit to:</strong> <a href=\"https://en.wikipedia.org/wiki/User%3AChasemp\" target=\"_blank\" rel=\"noopener\">User:Chasemp</a></p>\n    <p><strong>Summary:</strong> No edit summary</p>\n    <p><strong>Size change:</strong> <span style=\"color: #7cb342;\">+12 bytes</span></p>\n    <p><a href=\"https://en.wikipedia.org/w/index.php?title=User%3AChasemp&diff=887476434&oldid=672942728\" target=\"_blank\" rel=\"noopener\" style=\"color: var(--accent);\">View diff →</a></p>\n  ",
    "metadata": {
      "page": "User:Chasemp",
      "diff": 887476434,
      "oldid": 672942728,
      "size_delta": 12,
      "comment": "No edit summary"
    }
  },
  {
    "id": "wikipedia:886228014",
    "type": "wikipedia",
    "timestamp": "2019-03-04T23:23:29Z",
    "title": "edited \"Christopher Award\"",
    "summary": "Ken Burns wins the lifetime achievement award in 2018.  The chrisophers.org site is very difficult to reference as the URLs are reused but for now the 2018 awards are at this generic path. (+109 bytes",
    "url": "https://en.wikipedia.org/w/index.php?title=Christopher%20Award&diff=886228014&oldid=886227144",
    "content_html": "\n    <p><strong>Edit to:</strong> <a href=\"https://en.wikipedia.org/wiki/Christopher%20Award\" target=\"_blank\" rel=\"noopener\">Christopher Award</a></p>\n    <p><strong>Summary:</strong> Ken Burns wins the lifetime achievement award in 2018.  The chrisophers.org site is very difficult to reference as the URLs are reused but for now the 2018 awards are at this generic path.</p>\n    <p><strong>Size change:</strong> <span style=\"color: #7cb342;\">+109 bytes</span></p>\n    <p><a href=\"https://en.wikipedia.org/w/index.php?title=Christopher%20Award&diff=886228014&oldid=886227144\" target=\"_blank\" rel=\"noopener\" style=\"color: var(--accent);\">View diff →</a></p>\n  ",
    "metadata": {
      "page": "Christopher Award",
      "diff": 886228014,
      "oldid": 886227144,
      "size_delta": 109,
      "comment": "Ken Burns wins the lifetime achievement award in 2018.  The chrisophers.org site is very difficult to reference as the URLs are reused but for now the 2018 awards are at this generic path."
    }
  },
  {
    "id": "wikipedia:886227144",
    "type": "wikipedia",
    "timestamp": "2019-03-04T23:17:56Z",
    "title": "edited \"Christopher Award\"",
    "summary": "kaffir boy won the christopher award (as noted on its page) in 1987 , difficult to find sources for the exact year though it's reported widely 1986/7. (+283 bytes)",
    "url": "https://en.wikipedia.org/w/index.php?title=Christopher%20Award&diff=886227144&oldid=870035713",
    "content_html": "\n    <p><strong>Edit to:</strong> <a href=\"https://en.wikipedia.org/wiki/Christopher%20Award\" target=\"_blank\" rel=\"noopener\">Christopher Award</a></p>\n    <p><strong>Summary:</strong> kaffir boy won the christopher award (as noted on its page) in 1987 , difficult to find sources for the exact year though it's reported widely 1986/7.</p>\n    <p><strong>Size change:</strong> <span style=\"color: #7cb342;\">+283 bytes</span></p>\n    <p><a href=\"https://en.wikipedia.org/w/index.php?title=Christopher%20Award&diff=886227144&oldid=870035713\" target=\"_blank\" rel=\"noopener\" style=\"color: var(--accent);\">View diff →</a></p>\n  ",
    "metadata": {
      "page": "Christopher Award",
      "diff": 886227144,
      "oldid": 870035713,
      "size_delta": 283,
      "comment": "kaffir boy won the christopher award (as noted on its page) in 1987 , difficult to find sources for the exact year though it's reported widely 1986/7."
    }
  },
  {
    "id": "wikipedia:886222712",
    "type": "wikipedia",
    "timestamp": "2019-03-04T22:41:51Z",
    "title": "edited \"Kaffir Boy\"",
    "summary": "Update content regarding the smiths and how they helped Mark, the book puts emphasis on comic books in this case.  The phrase \"liberal whites\" is also used in the book to describe families such as the",
    "url": "https://en.wikipedia.org/w/index.php?title=Kaffir%20Boy&diff=886222712&oldid=882583503",
    "content_html": "\n    <p><strong>Edit to:</strong> <a href=\"https://en.wikipedia.org/wiki/Kaffir%20Boy\" target=\"_blank\" rel=\"noopener\">Kaffir Boy</a></p>\n    <p><strong>Summary:</strong> Update content regarding the smiths and how they helped Mark, the book puts emphasis on comic books in this case.  The phrase \"liberal whites\" is also used in the book to describe families such as the smiths.  Since Sam Smith is a real person I linked the name in the plot summary.</p>\n    <p><strong>Size change:</strong> <span style=\"color: #7cb342;\">+66 bytes</span></p>\n    <p><a href=\"https://en.wikipedia.org/w/index.php?title=Kaffir%20Boy&diff=886222712&oldid=882583503\" target=\"_blank\" rel=\"noopener\" style=\"color: var(--accent);\">View diff →</a></p>\n  ",
    "metadata": {
      "page": "Kaffir Boy",
      "diff": 886222712,
      "oldid": 882583503,
      "size_delta": 66,
      "comment": "Update content regarding the smiths and how they helped Mark, the book puts emphasis on comic books in this case.  The phrase \"liberal whites\" is also used in the book to describe families such as the smiths.  Since Sam Smith is a real person I linked the name in the plot summary."
    }
  },
  {
    "id": "wikipedia:885725943",
    "type": "wikipedia",
    "timestamp": "2019-03-01T22:27:57Z",
    "title": "edited \"Wikipedia:Mailing lists\"",
    "summary": "nonmembers is non-members (+1 bytes)",
    "url": "https://en.wikipedia.org/w/index.php?title=Wikipedia%3AMailing%20lists&diff=885725943&oldid=883842760",
    "content_html": "\n    <p><strong>Edit to:</strong> <a href=\"https://en.wikipedia.org/wiki/Wikipedia%3AMailing%20lists\" target=\"_blank\" rel=\"noopener\">Wikipedia:Mailing lists</a></p>\n    <p><strong>Summary:</strong> nonmembers is non-members</p>\n    <p><strong>Size change:</strong> <span style=\"color: #7cb342;\">+1 bytes</span></p>\n    <p><a href=\"https://en.wikipedia.org/w/index.php?title=Wikipedia%3AMailing%20lists&diff=885725943&oldid=883842760\" target=\"_blank\" rel=\"noopener\" style=\"color: var(--accent);\">View diff →</a></p>\n  ",
    "metadata": {
      "page": "Wikipedia:Mailing lists",
      "diff": 885725943,
      "oldid": 883842760,
      "size_delta": 1,
      "comment": "nonmembers is non-members"
    }
  },
  {
    "id": "wikipedia:885717842",
    "type": "wikipedia",
    "timestamp": "2019-03-01T21:12:58Z",
    "title": "edited \"Buchi Emecheta\"",
    "summary": "Link to Second Class Citizen article and remove hyphen.  Although generally this would be a compound adjective in this case it is a literal book title and neither the publisher's site (http://www.geor",
    "url": "https://en.wikipedia.org/w/index.php?title=Buchi%20Emecheta&diff=885717842&oldid=870346400",
    "content_html": "\n    <p><strong>Edit to:</strong> <a href=\"https://en.wikipedia.org/wiki/Buchi%20Emecheta\" target=\"_blank\" rel=\"noopener\">Buchi Emecheta</a></p>\n    <p><strong>Summary:</strong> Link to Second Class Citizen article and remove hyphen.  Although generally this would be a compound adjective in this case it is a literal book title and neither the publisher's site (http://www.georgebraziller.com/second-class-citizen)  nor the book cover indicate their is a hyphen.</p>\n    <p><strong>Size change:</strong> <span style=\"color: #7cb342;\">+32 bytes</span></p>\n    <p><a href=\"https://en.wikipedia.org/w/index.php?title=Buchi%20Emecheta&diff=885717842&oldid=870346400\" target=\"_blank\" rel=\"noopener\" style=\"color: var(--accent);\">View diff →</a></p>\n  ",
    "metadata": {
      "page": "Buchi Emecheta",
      "diff": 885717842,
      "oldid": 870346400,
      "size_delta": 32,
      "comment": "Link to Second Class Citizen article and remove hyphen.  Although generally this would be a compound adjective in this case it is a literal book title and neither the publisher's site (http://www.georgebraziller.com/second-class-citizen)  nor the book cover indicate their is a hyphen."
    }
  },
  {
    "id": "wikipedia:885717463",
    "type": "wikipedia",
    "timestamp": "2019-03-01T21:10:34Z",
    "title": "created or expanded \"Second Class Citizen (novel)\"",
    "summary": "initial page with sources (+3007 bytes)",
    "url": "https://en.wikipedia.org/w/index.php?title=Second%20Class%20Citizen%20(novel)&diff=885717463&oldid=0",
    "content_html": "\n    <p><strong>Edit to:</strong> <a href=\"https://en.wikipedia.org/wiki/Second%20Class%20Citizen%20(novel)\" target=\"_blank\" rel=\"noopener\">Second Class Citizen (novel)</a></p>\n    <p><strong>Summary:</strong> initial page with sources</p>\n    <p><strong>Size change:</strong> <span style=\"color: #7cb342;\">+3007 bytes</span></p>\n    <p><a href=\"https://en.wikipedia.org/w/index.php?title=Second%20Class%20Citizen%20(novel)&diff=885717463&oldid=0\" target=\"_blank\" rel=\"noopener\" style=\"color: var(--accent);\">View diff →</a></p>\n  ",
    "metadata": {
      "page": "Second Class Citizen (novel)",
      "diff": 885717463,
      "oldid": 0,
      "size_delta": 3007,
      "comment": "initial page with sources"
    }
  },
  {
    "id": "wikipedia:885717311",
    "type": "wikipedia",
    "timestamp": "2019-03-01T21:09:22Z",
    "title": "edited \"User:Chasemp/Second Class Citizen (Book)\"",
    "summary": "No edit summary (-5 bytes)",
    "url": "https://en.wikipedia.org/w/index.php?title=User%3AChasemp%2FSecond%20Class%20Citizen%20(Book)&diff=885717311&oldid=885717092",
    "content_html": "\n    <p><strong>Edit to:</strong> <a href=\"https://en.wikipedia.org/wiki/User%3AChasemp%2FSecond%20Class%20Citizen%20(Book)\" target=\"_blank\" rel=\"noopener\">User:Chasemp/Second Class Citizen (Book)</a></p>\n    <p><strong>Summary:</strong> No edit summary</p>\n    <p><strong>Size change:</strong> <span style=\"color: #e53935;\">-5 bytes</span></p>\n    <p><a href=\"https://en.wikipedia.org/w/index.php?title=User%3AChasemp%2FSecond%20Class%20Citizen%20(Book)&diff=885717311&oldid=885717092\" target=\"_blank\" rel=\"noopener\" style=\"color: var(--accent);\">View diff →</a></p>\n  ",
    "metadata": {
      "page": "User:Chasemp/Second Class Citizen (Book)",
      "diff": 885717311,
      "oldid": 885717092,
      "size_delta": -5,
      "comment": "No edit summary"
    }
  },
  {
    "id": "wikipedia:885717092",
    "type": "wikipedia",
    "timestamp": "2019-03-01T21:07:36Z",
    "title": "edited \"User:Chasemp/Second Class Citizen (Book)\"",
    "summary": "No edit summary (-66 bytes)",
    "url": "https://en.wikipedia.org/w/index.php?title=User%3AChasemp%2FSecond%20Class%20Citizen%20(Book)&diff=885717092&oldid=885716243",
    "content_html": "\n    <p><strong>Edit to:</strong> <a href=\"https://en.wikipedia.org/wiki/User%3AChasemp%2FSecond%20Class%20Citizen%20(Book)\" target=\"_blank\" rel=\"noopener\">User:Chasemp/Second Class Citizen (Book)</a></p>\n    <p><strong>Summary:</strong> No edit summary</p>\n    <p><strong>Size change:</strong> <span style=\"color: #e53935;\">-66 bytes</span></p>\n    <p><a href=\"https://en.wikipedia.org/w/index.php?title=User%3AChasemp%2FSecond%20Class%20Citizen%20(Book)&diff=885717092&oldid=885716243\" target=\"_blank\" rel=\"noopener\" style=\"color: var(--accent);\">View diff →</a></p>\n  ",
    "metadata": {
      "page": "User:Chasemp/Second Class Citizen (Book)",
      "diff": 885717092,
      "oldid": 885716243,
      "size_delta": -66,
      "comment": "No edit summary"
    }
  },
  {
    "id": "wikipedia:885716243",
    "type": "wikipedia",
    "timestamp": "2019-03-01T21:01:04Z",
    "title": "edited \"User:Chasemp/Second Class Citizen (Book)\"",
    "summary": "No edit summary (+357 bytes)",
    "url": "https://en.wikipedia.org/w/index.php?title=User%3AChasemp%2FSecond%20Class%20Citizen%20(Book)&diff=885716243&oldid=885715095",
    "content_html": "\n    <p><strong>Edit to:</strong> <a href=\"https://en.wikipedia.org/wiki/User%3AChasemp%2FSecond%20Class%20Citizen%20(Book)\" target=\"_blank\" rel=\"noopener\">User:Chasemp/Second Class Citizen (Book)</a></p>\n    <p><strong>Summary:</strong> No edit summary</p>\n    <p><strong>Size change:</strong> <span style=\"color: #7cb342;\">+357 bytes</span></p>\n    <p><a href=\"https://en.wikipedia.org/w/index.php?title=User%3AChasemp%2FSecond%20Class%20Citizen%20(Book)&diff=885716243&oldid=885715095\" target=\"_blank\" rel=\"noopener\" style=\"color: var(--accent);\">View diff →</a></p>\n  ",
    "metadata": {
      "page": "User:Chasemp/Second Class Citizen (Book)",
      "diff": 885716243,
      "oldid": 885715095,
      "size_delta": 357,
      "comment": "No edit summary"
    }
  },
  {
    "id": "wikipedia:885715095",
    "type": "wikipedia",
    "timestamp": "2019-03-01T20:51:44Z",
    "title": "edited \"User:Chasemp/Second Class Citizen (Book)\"",
    "summary": "No edit summary (+428 bytes)",
    "url": "https://en.wikipedia.org/w/index.php?title=User%3AChasemp%2FSecond%20Class%20Citizen%20(Book)&diff=885715095&oldid=885714043",
    "content_html": "\n    <p><strong>Edit to:</strong> <a href=\"https://en.wikipedia.org/wiki/User%3AChasemp%2FSecond%20Class%20Citizen%20(Book)\" target=\"_blank\" rel=\"noopener\">User:Chasemp/Second Class Citizen (Book)</a></p>\n    <p><strong>Summary:</strong> No edit summary</p>\n    <p><strong>Size change:</strong> <span style=\"color: #7cb342;\">+428 bytes</span></p>\n    <p><a href=\"https://en.wikipedia.org/w/index.php?title=User%3AChasemp%2FSecond%20Class%20Citizen%20(Book)&diff=885715095&oldid=885714043\" target=\"_blank\" rel=\"noopener\" style=\"color: var(--accent);\">View diff →</a></p>\n  ",
    "metadata": {
      "page": "User:Chasemp/Second Class Citizen (Book)",
      "diff": 885715095,
      "oldid": 885714043,
      "size_delta": 428,
      "comment": "No edit summary"
    }
  },
  {
    "id": "wikipedia:885714043",
    "type": "wikipedia",
    "timestamp": "2019-03-01T20:43:14Z",
    "title": "edited \"User:Chasemp/Second Class Citizen (Book)\"",
    "summary": "No edit summary (-30 bytes)",
    "url": "https://en.wikipedia.org/w/index.php?title=User%3AChasemp%2FSecond%20Class%20Citizen%20(Book)&diff=885714043&oldid=885713839",
    "content_html": "\n    <p><strong>Edit to:</strong> <a href=\"https://en.wikipedia.org/wiki/User%3AChasemp%2FSecond%20Class%20Citizen%20(Book)\" target=\"_blank\" rel=\"noopener\">User:Chasemp/Second Class Citizen (Book)</a></p>\n    <p><strong>Summary:</strong> No edit summary</p>\n    <p><strong>Size change:</strong> <span style=\"color: #e53935;\">-30 bytes</span></p>\n    <p><a href=\"https://en.wikipedia.org/w/index.php?title=User%3AChasemp%2FSecond%20Class%20Citizen%20(Book)&diff=885714043&oldid=885713839\" target=\"_blank\" rel=\"noopener\" style=\"color: var(--accent);\">View diff →</a></p>\n  ",
    "metadata": {
      "page": "User:Chasemp/Second Class Citizen (Book)",
      "diff": 885714043,
      "oldid": 885713839,
      "size_delta": -30,
      "comment": "No edit summary"
    }
  },
  {
    "id": "wikipedia:885713839",
    "type": "wikipedia",
    "timestamp": "2019-03-01T20:41:54Z",
    "title": "trimmed \"User:Chasemp/Second Class Citizen (Book)\"",
    "summary": "No edit summary (-2005 bytes)",
    "url": "https://en.wikipedia.org/w/index.php?title=User%3AChasemp%2FSecond%20Class%20Citizen%20(Book)&diff=885713839&oldid=885711700",
    "content_html": "\n    <p><strong>Edit to:</strong> <a href=\"https://en.wikipedia.org/wiki/User%3AChasemp%2FSecond%20Class%20Citizen%20(Book)\" target=\"_blank\" rel=\"noopener\">User:Chasemp/Second Class Citizen (Book)</a></p>\n    <p><strong>Summary:</strong> No edit summary</p>\n    <p><strong>Size change:</strong> <span style=\"color: #e53935;\">-2005 bytes</span></p>\n    <p><a href=\"https://en.wikipedia.org/w/index.php?title=User%3AChasemp%2FSecond%20Class%20Citizen%20(Book)&diff=885713839&oldid=885711700\" target=\"_blank\" rel=\"noopener\" style=\"color: var(--accent);\">View diff →</a></p>\n  ",
    "metadata": {
      "page": "User:Chasemp/Second Class Citizen (Book)",
      "diff": 885713839,
      "oldid": 885711700,
      "size_delta": -2005,
      "comment": "No edit summary"
    }
  },
  {
    "id": "wikipedia:885711700",
    "type": "wikipedia",
    "timestamp": "2019-03-01T20:25:44Z",
    "title": "trimmed \"User:Chasemp/Second Class Citizen (Book)\"",
    "summary": "No edit summary (-1623 bytes)",
    "url": "https://en.wikipedia.org/w/index.php?title=User%3AChasemp%2FSecond%20Class%20Citizen%20(Book)&diff=885711700&oldid=885711428",
    "content_html": "\n    <p><strong>Edit to:</strong> <a href=\"https://en.wikipedia.org/wiki/User%3AChasemp%2FSecond%20Class%20Citizen%20(Book)\" target=\"_blank\" rel=\"noopener\">User:Chasemp/Second Class Citizen (Book)</a></p>\n    <p><strong>Summary:</strong> No edit summary</p>\n    <p><strong>Size change:</strong> <span style=\"color: #e53935;\">-1623 bytes</span></p>\n    <p><a href=\"https://en.wikipedia.org/w/index.php?title=User%3AChasemp%2FSecond%20Class%20Citizen%20(Book)&diff=885711700&oldid=885711428\" target=\"_blank\" rel=\"noopener\" style=\"color: var(--accent);\">View diff →</a></p>\n  ",
    "metadata": {
      "page": "User:Chasemp/Second Class Citizen (Book)",
      "diff": 885711700,
      "oldid": 885711428,
      "size_delta": -1623,
      "comment": "No edit summary"
    }
  },
  {
    "id": "wikipedia:885711428",
    "type": "wikipedia",
    "timestamp": "2019-03-01T20:23:26Z",
    "title": "edited \"User:Chasemp/Second Class Citizen (Book)\"",
    "summary": "No edit summary (-29 bytes)",
    "url": "https://en.wikipedia.org/w/index.php?title=User%3AChasemp%2FSecond%20Class%20Citizen%20(Book)&diff=885711428&oldid=885711395",
    "content_html": "\n    <p><strong>Edit to:</strong> <a href=\"https://en.wikipedia.org/wiki/User%3AChasemp%2FSecond%20Class%20Citizen%20(Book)\" target=\"_blank\" rel=\"noopener\">User:Chasemp/Second Class Citizen (Book)</a></p>\n    <p><strong>Summary:</strong> No edit summary</p>\n    <p><strong>Size change:</strong> <span style=\"color: #e53935;\">-29 bytes</span></p>\n    <p><a href=\"https://en.wikipedia.org/w/index.php?title=User%3AChasemp%2FSecond%20Class%20Citizen%20(Book)&diff=885711428&oldid=885711395\" target=\"_blank\" rel=\"noopener\" style=\"color: var(--accent);\">View diff →</a></p>\n  ",
    "metadata": {
      "page": "User:Chasemp/Second Class Citizen (Book)",
      "diff": 885711428,
      "oldid": 885711395,
      "size_delta": -29,
      "comment": "No edit summary"
    }
  },
  {
    "id": "wikipedia:885711395",
    "type": "wikipedia",
    "timestamp": "2019-03-01T20:23:09Z",
    "title": "created or expanded \"User:Chasemp/Second Class Citizen (Book)\"",
    "summary": "[[WP:AES|←]]Created page with '{{Refimprove|date=May 2013}} {{infobox book | <!-- See [[Wikipedia:WikiProject Novels]] or [[Wikipedia:WikiProject Books]] --> | name          = The Bride Price...' (+59",
    "url": "https://en.wikipedia.org/w/index.php?title=User%3AChasemp%2FSecond%20Class%20Citizen%20(Book)&diff=885711395&oldid=0",
    "content_html": "\n    <p><strong>Edit to:</strong> <a href=\"https://en.wikipedia.org/wiki/User%3AChasemp%2FSecond%20Class%20Citizen%20(Book)\" target=\"_blank\" rel=\"noopener\">User:Chasemp/Second Class Citizen (Book)</a></p>\n    <p><strong>Summary:</strong> [[WP:AES|←]]Created page with '{{Refimprove|date=May 2013}} {{infobox book | <!-- See [[Wikipedia:WikiProject Novels]] or [[Wikipedia:WikiProject Books]] --> | name          = The Bride Price...'</p>\n    <p><strong>Size change:</strong> <span style=\"color: #7cb342;\">+5980 bytes</span></p>\n    <p><a href=\"https://en.wikipedia.org/w/index.php?title=User%3AChasemp%2FSecond%20Class%20Citizen%20(Book)&diff=885711395&oldid=0\" target=\"_blank\" rel=\"noopener\" style=\"color: var(--accent);\">View diff →</a></p>\n  ",
    "metadata": {
      "page": "User:Chasemp/Second Class Citizen (Book)",
      "diff": 885711395,
      "oldid": 0,
      "size_delta": 5980,
      "comment": "[[WP:AES|←]]Created page with '{{Refimprove|date=May 2013}} {{infobox book | <!-- See [[Wikipedia:WikiProject Novels]] or [[Wikipedia:WikiProject Books]] --> | name          = The Bride Price...'"
    }
  },
  {
    "id": "wikipedia:884633978",
    "type": "wikipedia",
    "timestamp": "2019-02-22T22:51:43Z",
    "title": "edited \"Wikipedia:Scripts++/Subscribe\"",
    "summary": "add chasemp for subscription (+62 bytes)",
    "url": "https://en.wikipedia.org/w/index.php?title=Wikipedia%3AScripts%2B%2B%2FSubscribe&diff=884633978&oldid=883851862",
    "content_html": "\n    <p><strong>Edit to:</strong> <a href=\"https://en.wikipedia.org/wiki/Wikipedia%3AScripts%2B%2B%2FSubscribe\" target=\"_blank\" rel=\"noopener\">Wikipedia:Scripts++/Subscribe</a></p>\n    <p><strong>Summary:</strong> add chasemp for subscription</p>\n    <p><strong>Size change:</strong> <span style=\"color: #7cb342;\">+62 bytes</span></p>\n    <p><a href=\"https://en.wikipedia.org/w/index.php?title=Wikipedia%3AScripts%2B%2B%2FSubscribe&diff=884633978&oldid=883851862\" target=\"_blank\" rel=\"noopener\" style=\"color: var(--accent);\">View diff →</a></p>\n  ",
    "metadata": {
      "page": "Wikipedia:Scripts++/Subscribe",
      "diff": 884633978,
      "oldid": 883851862,
      "size_delta": 62,
      "comment": "add chasemp for subscription"
    }
  },
  {
    "id": "wikipedia:884633162",
    "type": "wikipedia",
    "timestamp": "2019-02-22T22:43:55Z",
    "title": "edited \"Wikipedia:Wikipedia is a work in progress\"",
    "summary": "Update creation timeline to eighteen years per /wiki/Wikipedia (+1 bytes)",
    "url": "https://en.wikipedia.org/w/index.php?title=Wikipedia%3AWikipedia%20is%20a%20work%20in%20progress&diff=884633162&oldid=844314425",
    "content_html": "\n    <p><strong>Edit to:</strong> <a href=\"https://en.wikipedia.org/wiki/Wikipedia%3AWikipedia%20is%20a%20work%20in%20progress\" target=\"_blank\" rel=\"noopener\">Wikipedia:Wikipedia is a work in progress</a></p>\n    <p><strong>Summary:</strong> Update creation timeline to eighteen years per /wiki/Wikipedia</p>\n    <p><strong>Size change:</strong> <span style=\"color: #7cb342;\">+1 bytes</span></p>\n    <p><a href=\"https://en.wikipedia.org/w/index.php?title=Wikipedia%3AWikipedia%20is%20a%20work%20in%20progress&diff=884633162&oldid=844314425\" target=\"_blank\" rel=\"noopener\" style=\"color: var(--accent);\">View diff →</a></p>\n  ",
    "metadata": {
      "page": "Wikipedia:Wikipedia is a work in progress",
      "diff": 884633162,
      "oldid": 844314425,
      "size_delta": 1,
      "comment": "Update creation timeline to eighteen years per /wiki/Wikipedia"
    }
  },
  {
    "id": "wikipedia:884622408",
    "type": "wikipedia",
    "timestamp": "2019-02-22T21:07:36Z",
    "title": "edited \"Lee's Summit, Missouri\"",
    "summary": "this closed https://www.bizjournals.com/kansascity/news/2018/03/15/toys-r-us-lees-summit-distribution-center-closing.html (-44 bytes)",
    "url": "https://en.wikipedia.org/w/index.php?title=Lee's%20Summit%2C%20Missouri&diff=884622408&oldid=884045821",
    "content_html": "\n    <p><strong>Edit to:</strong> <a href=\"https://en.wikipedia.org/wiki/Lee's%20Summit%2C%20Missouri\" target=\"_blank\" rel=\"noopener\">Lee's Summit, Missouri</a></p>\n    <p><strong>Summary:</strong> this closed https://www.bizjournals.com/kansascity/news/2018/03/15/toys-r-us-lees-summit-distribution-center-closing.html</p>\n    <p><strong>Size change:</strong> <span style=\"color: #e53935;\">-44 bytes</span></p>\n    <p><a href=\"https://en.wikipedia.org/w/index.php?title=Lee's%20Summit%2C%20Missouri&diff=884622408&oldid=884045821\" target=\"_blank\" rel=\"noopener\" style=\"color: var(--accent);\">View diff →</a></p>\n  ",
    "metadata": {
      "page": "Lee's Summit, Missouri",
      "diff": 884622408,
      "oldid": 884045821,
      "size_delta": -44,
      "comment": "this closed https://www.bizjournals.com/kansascity/news/2018/03/15/toys-r-us-lees-summit-distribution-center-closing.html"
    }
  },
  {
    "id": "wikipedia:884606852",
    "type": "wikipedia",
    "timestamp": "2019-02-22T19:07:48Z",
    "title": "created or expanded \"Armpit fart\"",
    "summary": "initial article with references (+1649 bytes)",
    "url": "https://en.wikipedia.org/w/index.php?title=Armpit%20fart&diff=884606852&oldid=0",
    "content_html": "\n    <p><strong>Edit to:</strong> <a href=\"https://en.wikipedia.org/wiki/Armpit%20fart\" target=\"_blank\" rel=\"noopener\">Armpit fart</a></p>\n    <p><strong>Summary:</strong> initial article with references</p>\n    <p><strong>Size change:</strong> <span style=\"color: #7cb342;\">+1649 bytes</span></p>\n    <p><a href=\"https://en.wikipedia.org/w/index.php?title=Armpit%20fart&diff=884606852&oldid=0\" target=\"_blank\" rel=\"noopener\" style=\"color: var(--accent);\">View diff →</a></p>\n  ",
    "metadata": {
      "page": "Armpit fart",
      "diff": 884606852,
      "oldid": 0,
      "size_delta": 1649,
      "comment": "initial article with references"
    }
  },
  {
    "id": "wikipedia:882073499",
    "type": "wikipedia",
    "timestamp": "2019-02-06T17:31:56Z",
    "title": "edited \"Suelo\"",
    "summary": "Add update that suelo is now using money in some capacity as detailed in Tedx talk (+294 bytes)",
    "url": "https://en.wikipedia.org/w/index.php?title=Suelo&diff=882073499&oldid=858030753",
    "content_html": "\n    <p><strong>Edit to:</strong> <a href=\"https://en.wikipedia.org/wiki/Suelo\" target=\"_blank\" rel=\"noopener\">Suelo</a></p>\n    <p><strong>Summary:</strong> Add update that suelo is now using money in some capacity as detailed in Tedx talk</p>\n    <p><strong>Size change:</strong> <span style=\"color: #7cb342;\">+294 bytes</span></p>\n    <p><a href=\"https://en.wikipedia.org/w/index.php?title=Suelo&diff=882073499&oldid=858030753\" target=\"_blank\" rel=\"noopener\" style=\"color: var(--accent);\">View diff →</a></p>\n  ",
    "metadata": {
      "page": "Suelo",
      "diff": 882073499,
      "oldid": 858030753,
      "size_delta": 294,
      "comment": "Add update that suelo is now using money in some capacity as detailed in Tedx talk"
    }
  },
  {
    "id": "wikipedia:851353930",
    "type": "wikipedia",
    "timestamp": "2018-07-21T18:21:05Z",
    "title": "created \"User:Chasemp/common.js\"",
    "summary": "[[WP:AES|←]]Created page with 'importScript('User:Numbermaniac/goToTop.js'); // [[User:Numbermaniac/goToTop.js]]' (+81 bytes)",
    "url": "https://en.wikipedia.org/w/index.php?title=User%3AChasemp%2Fcommon.js&diff=851353930&oldid=0",
    "content_html": "\n    <p><strong>Edit to:</strong> <a href=\"https://en.wikipedia.org/wiki/User%3AChasemp%2Fcommon.js\" target=\"_blank\" rel=\"noopener\">User:Chasemp/common.js</a></p>\n    <p><strong>Summary:</strong> [[WP:AES|←]]Created page with 'importScript('User:Numbermaniac/goToTop.js'); // [[User:Numbermaniac/goToTop.js]]'</p>\n    <p><strong>Size change:</strong> <span style=\"color: #7cb342;\">+81 bytes</span></p>\n    <p><a href=\"https://en.wikipedia.org/w/index.php?title=User%3AChasemp%2Fcommon.js&diff=851353930&oldid=0\" target=\"_blank\" rel=\"noopener\" style=\"color: var(--accent);\">View diff →</a></p>\n  ",
    "metadata": {
      "page": "User:Chasemp/common.js",
      "diff": 851353930,
      "oldid": 0,
      "size_delta": 81,
      "comment": "[[WP:AES|←]]Created page with 'importScript('User:Numbermaniac/goToTop.js'); // [[User:Numbermaniac/goToTop.js]]'"
    }
  },
  {
    "id": "wikipedia:799602676",
    "type": "wikipedia",
    "timestamp": "2017-09-08T18:31:01Z",
    "title": "edited \"Ignite talk\"",
    "summary": "These terms have become synonymous but at the moment \"ignite talk\" is hard to find. (+28 bytes)",
    "url": "https://en.wikipedia.org/w/index.php?title=Ignite%20talk&diff=799602676&oldid=0",
    "content_html": "\n    <p><strong>Edit to:</strong> <a href=\"https://en.wikipedia.org/wiki/Ignite%20talk\" target=\"_blank\" rel=\"noopener\">Ignite talk</a></p>\n    <p><strong>Summary:</strong> These terms have become synonymous but at the moment \"ignite talk\" is hard to find.</p>\n    <p><strong>Size change:</strong> <span style=\"color: #7cb342;\">+28 bytes</span></p>\n    <p><a href=\"https://en.wikipedia.org/w/index.php?title=Ignite%20talk&diff=799602676&oldid=0\" target=\"_blank\" rel=\"noopener\" style=\"color: var(--accent);\">View diff →</a></p>\n  ",
    "metadata": {
      "page": "Ignite talk",
      "diff": 799602676,
      "oldid": 0,
      "size_delta": 28,
      "comment": "These terms have become synonymous but at the moment \"ignite talk\" is hard to find."
    }
  },
  {
    "id": "wikipedia:799553402",
    "type": "wikipedia",
    "timestamp": "2017-09-08T12:16:00Z",
    "title": "edited \"Lightning talk\"",
    "summary": "Note lighting talks are often referred to now as just \"ignite talks\" and add ignite karaoke with reference (+416 bytes)",
    "url": "https://en.wikipedia.org/w/index.php?title=Lightning%20talk&diff=799553402&oldid=798637451",
    "content_html": "\n    <p><strong>Edit to:</strong> <a href=\"https://en.wikipedia.org/wiki/Lightning%20talk\" target=\"_blank\" rel=\"noopener\">Lightning talk</a></p>\n    <p><strong>Summary:</strong> Note lighting talks are often referred to now as just \"ignite talks\" and add ignite karaoke with reference</p>\n    <p><strong>Size change:</strong> <span style=\"color: #7cb342;\">+416 bytes</span></p>\n    <p><a href=\"https://en.wikipedia.org/w/index.php?title=Lightning%20talk&diff=799553402&oldid=798637451\" target=\"_blank\" rel=\"noopener\" style=\"color: var(--accent);\">View diff →</a></p>\n  ",
    "metadata": {
      "page": "Lightning talk",
      "diff": 799553402,
      "oldid": 798637451,
      "size_delta": 416,
      "comment": "Note lighting talks are often referred to now as just \"ignite talks\" and add ignite karaoke with reference"
    }
  },
  {
    "id": "wikipedia:799552783",
    "type": "wikipedia",
    "timestamp": "2017-09-08T12:10:09Z",
    "title": "created \"User:Chasemp/sandbox\"",
    "summary": "[[WP:AES|←]]Created page with '{{User sandbox}} <!-- EDIT BELOW THIS LINE -->  Netfilter represents a set of [[hooking|hooks]] inside the Linux kernel, allowing specific [[kernel module]]s to...' (+62",
    "url": "https://en.wikipedia.org/w/index.php?title=User%3AChasemp%2Fsandbox&diff=799552783&oldid=0",
    "content_html": "\n    <p><strong>Edit to:</strong> <a href=\"https://en.wikipedia.org/wiki/User%3AChasemp%2Fsandbox\" target=\"_blank\" rel=\"noopener\">User:Chasemp/sandbox</a></p>\n    <p><strong>Summary:</strong> [[WP:AES|←]]Created page with '{{User sandbox}} <!-- EDIT BELOW THIS LINE -->  Netfilter represents a set of [[hooking|hooks]] inside the Linux kernel, allowing specific [[kernel module]]s to...'</p>\n    <p><strong>Size change:</strong> <span style=\"color: #7cb342;\">+628 bytes</span></p>\n    <p><a href=\"https://en.wikipedia.org/w/index.php?title=User%3AChasemp%2Fsandbox&diff=799552783&oldid=0\" target=\"_blank\" rel=\"noopener\" style=\"color: var(--accent);\">View diff →</a></p>\n  ",
    "metadata": {
      "page": "User:Chasemp/sandbox",
      "diff": 799552783,
      "oldid": 0,
      "size_delta": 628,
      "comment": "[[WP:AES|←]]Created page with '{{User sandbox}} <!-- EDIT BELOW THIS LINE -->  Netfilter represents a set of [[hooking|hooks]] inside the Linux kernel, allowing specific [[kernel module]]s to...'"
    }
  },
  {
    "id": "wikipedia:760578340",
    "type": "wikipedia",
    "timestamp": "2017-01-17T21:22:19Z",
    "title": "edited \"Ward Cunningham\"",
    "summary": "No edit summary (+240 bytes)",
    "url": "https://en.wikipedia.org/w/index.php?title=Ward%20Cunningham&diff=760578340&oldid=759294868",
    "content_html": "\n    <p><strong>Edit to:</strong> <a href=\"https://en.wikipedia.org/wiki/Ward%20Cunningham\" target=\"_blank\" rel=\"noopener\">Ward Cunningham</a></p>\n    <p><strong>Summary:</strong> No edit summary</p>\n    <p><strong>Size change:</strong> <span style=\"color: #7cb342;\">+240 bytes</span></p>\n    <p><a href=\"https://en.wikipedia.org/w/index.php?title=Ward%20Cunningham&diff=760578340&oldid=759294868\" target=\"_blank\" rel=\"noopener\" style=\"color: var(--accent);\">View diff →</a></p>\n  ",
    "metadata": {
      "page": "Ward Cunningham",
      "diff": 760578340,
      "oldid": 759294868,
      "size_delta": 240,
      "comment": "No edit summary"
    }
  },
  {
    "id": "wikipedia:758122715",
    "type": "wikipedia",
    "timestamp": "2017-01-03T16:46:57Z",
    "title": "edited \"Douglas Brunt\"",
    "summary": "Make 'bestseller' plural -- https://en.wiktionary.org/wiki/bestsellers#English (+1 bytes)",
    "url": "https://en.wikipedia.org/w/index.php?title=Douglas%20Brunt&diff=758122715&oldid=749883794",
    "content_html": "\n    <p><strong>Edit to:</strong> <a href=\"https://en.wikipedia.org/wiki/Douglas%20Brunt\" target=\"_blank\" rel=\"noopener\">Douglas Brunt</a></p>\n    <p><strong>Summary:</strong> Make 'bestseller' plural -- https://en.wiktionary.org/wiki/bestsellers#English</p>\n    <p><strong>Size change:</strong> <span style=\"color: #7cb342;\">+1 bytes</span></p>\n    <p><a href=\"https://en.wikipedia.org/w/index.php?title=Douglas%20Brunt&diff=758122715&oldid=749883794\" target=\"_blank\" rel=\"noopener\" style=\"color: var(--accent);\">View diff →</a></p>\n  ",
    "metadata": {
      "page": "Douglas Brunt",
      "diff": 758122715,
      "oldid": 749883794,
      "size_delta": 1,
      "comment": "Make 'bestseller' plural -- https://en.wiktionary.org/wiki/bestsellers#English"
    }
  },
  {
    "id": "wikipedia:684496077",
    "type": "wikipedia",
    "timestamp": "2015-10-07T00:13:07Z",
    "title": "edited \"Netfilter\"",
    "summary": "Grammer update (+4 bytes)",
    "url": "https://en.wikipedia.org/w/index.php?title=Netfilter&diff=684496077&oldid=665633134",
    "content_html": "\n    <p><strong>Edit to:</strong> <a href=\"https://en.wikipedia.org/wiki/Netfilter\" target=\"_blank\" rel=\"noopener\">Netfilter</a></p>\n    <p><strong>Summary:</strong> Grammer update</p>\n    <p><strong>Size change:</strong> <span style=\"color: #7cb342;\">+4 bytes</span></p>\n    <p><a href=\"https://en.wikipedia.org/w/index.php?title=Netfilter&diff=684496077&oldid=665633134\" target=\"_blank\" rel=\"noopener\" style=\"color: var(--accent);\">View diff →</a></p>\n  ",
    "metadata": {
      "page": "Netfilter",
      "diff": 684496077,
      "oldid": 665633134,
      "size_delta": 4,
      "comment": "Grammer update"
    }
  },
  {
    "id": "wikipedia:672942728",
    "type": "wikipedia",
    "timestamp": "2015-07-24T22:50:34Z",
    "title": "created \"User:Chasemp\"",
    "summary": "[[WP:AES|←]]Created page with 'All edits and work done with this account are my personal views and efforts.  I'm trying to figure this out so please be gentle :)' (+130 bytes)",
    "url": "https://en.wikipedia.org/w/index.php?title=User%3AChasemp&diff=672942728&oldid=0",
    "content_html": "\n    <p><strong>Edit to:</strong> <a href=\"https://en.wikipedia.org/wiki/User%3AChasemp\" target=\"_blank\" rel=\"noopener\">User:Chasemp</a></p>\n    <p><strong>Summary:</strong> [[WP:AES|←]]Created page with 'All edits and work done with this account are my personal views and efforts.  I'm trying to figure this out so please be gentle :)'</p>\n    <p><strong>Size change:</strong> <span style=\"color: #7cb342;\">+130 bytes</span></p>\n    <p><a href=\"https://en.wikipedia.org/w/index.php?title=User%3AChasemp&diff=672942728&oldid=0\" target=\"_blank\" rel=\"noopener\" style=\"color: var(--accent);\">View diff →</a></p>\n  ",
    "metadata": {
      "page": "User:Chasemp",
      "diff": 672942728,
      "oldid": 0,
      "size_delta": 130,
      "comment": "[[WP:AES|←]]Created page with 'All edits and work done with this account are my personal views and efforts.  I'm trying to figure this out so please be gentle :)'"
    }
  },
  {
    "id": "wikipedia:672942609",
    "type": "wikipedia",
    "timestamp": "2015-07-24T22:49:30Z",
    "title": "edited \"Waupaca (town), Wisconsin\"",
    "summary": "/* Notable people */ (+41 bytes)",
    "url": "https://en.wikipedia.org/w/index.php?title=Waupaca%20(town)%2C%20Wisconsin&diff=672942609&oldid=643514332",
    "content_html": "\n    <p><strong>Edit to:</strong> <a href=\"https://en.wikipedia.org/wiki/Waupaca%20(town)%2C%20Wisconsin\" target=\"_blank\" rel=\"noopener\">Waupaca (town), Wisconsin</a></p>\n    <p><strong>Summary:</strong> /* Notable people */</p>\n    <p><strong>Size change:</strong> <span style=\"color: #7cb342;\">+41 bytes</span></p>\n    <p><a href=\"https://en.wikipedia.org/w/index.php?title=Waupaca%20(town)%2C%20Wisconsin&diff=672942609&oldid=643514332\" target=\"_blank\" rel=\"noopener\" style=\"color: var(--accent);\">View diff →</a></p>\n  ",
    "metadata": {
      "page": "Waupaca (town), Wisconsin",
      "diff": 672942609,
      "oldid": 643514332,
      "size_delta": 41,
      "comment": "/* Notable people */"
    }
  }
]